{
  "$schema": "https://json.schemastore.org/tsconfig",
  "compilerOptions": {
    "target": "ES2022",
    "module": "ESNext",
    "lib": ["ES2022"],
    "moduleResolution": "Bundler",
    "resolveJsonModule": true,
    "allowJs": false,
    "checkJs": false,
    "jsx": "react-jsx",
    "declaration": true,
    "declarationMap": true,
    "sourceMap": true,
    "outDir": "./dist",
    "rootDir": "./src",
    "composite": false,
    "removeComments": true,
    "isolatedModules": true,
    "allowSyntheticDefaultImports": true,
    "esModuleInterop": true,
    "forceConsistentCasingInFileNames": true,
    "strict": true,
    "noUnusedLocals": true,
    "noUnusedParameters": true,
    "noImplicitReturns": true,
    "noFallthroughCasesInSwitch": true,
    "skipLibCheck": true,
    "types": ["node"]
  },
  "include": ["src/**/*"],
  "exclude": ["node_modules", "dist", "**/*.spec.ts", "**/*.test.ts"]
}
